easygeo.py
easygeo-0.0.6.dist-info/LICENCE.txt
easygeo-0.0.6.dist-info/METADATA
easygeo-0.0.6.dist-info/WHEEL
easygeo-0.0.6.dist-info/top_level.txt
easygeo-0.0.6.dist-info/RECORD
