Metadata-Version: 2.1
Name: easygeo
Version: 0.0.6
Summary: Simple library that allows to geocode using Nominatim or Google V3 API
Home-page: https://github.com/CubelliJ/easyGeo
Author: Joaquin Cubelli
Author-email: jcubellidl@gmail.com
License: UNKNOWN
Platform: UNKNOWN
Classifier: Development Status :: 2 - Pre-Alpha
Classifier: Programming Language :: Python :: 3
Classifier: License :: OSI Approved :: MIT License
Classifier: Operating System :: POSIX :: Linux
Classifier: Operating System :: Unix
Classifier: Operating System :: MacOS
License-File: LICENCE.txt
Requires-Dist: geopy
Requires-Dist: pandas
